staticbackend/__init__.py
staticbackend/base.py
staticbackend/config.py
staticbackend/database.py
staticbackend/errors.py
staticbackend/forms.py
staticbackend/staticbackend.py
staticbackend/storage.py
staticbackend/user.py
staticbackend/version.py
staticbackend-0.1.1.dist-info/LICENSE
staticbackend-0.1.1.dist-info/WHEEL
staticbackend-0.1.1.dist-info/METADATA
staticbackend-0.1.1.dist-info/RECORD
